README.md
setup.cfg
setup.py
jisho/__init__.py
pyjisho.egg-info/PKG-INFO
pyjisho.egg-info/SOURCES.txt
pyjisho.egg-info/dependency_links.txt
pyjisho.egg-info/requires.txt
pyjisho.egg-info/top_level.txt