Metadata-Version: 2.1
Name: pyjisho
Version: 0.1.0
Summary: Python HTTP client for the Jisho.org search API.
Home-page: https://github.com/matthewmpalen/pyjisho
Author: Matt Palen
License: MIT
Download-URL: https://github.com/matthewmpalen/pyjisho/archive/0.1.0.tar.gz
Project-URL: Bug Reports, https://github.com/matthewmpalen/pyjisho/issues
Keywords: Japanese,English,translation,dictionary,language,jisho,辞書,じしょ
Platform: UNKNOWN
Classifier: Development Status :: 5 - Production/Stable
Classifier: Intended Audience :: Developers
Classifier: Programming Language :: Python
Classifier: Programming Language :: Python :: 3.8
Classifier: Topic :: Software Development :: Libraries :: Python Modules
